AUTHORS.rst
BUG_REPORTS.rst
CONTRIBUTING.rst
LICENSE
MANIFEST.in
README.rst
requirements.txt
setup.cfg
setup.py
test.py
test_requirements.txt
tox.ini
docs/conf.py
docs/index.rst
spex/__init__.py
spex/args.py
spex/artifact_server.py
spex/config.py
spex/context.py
spex/entrypoint.py
spex/runner.py
spex/utils.py
spex.egg-info/PKG-INFO
spex.egg-info/SOURCES.txt
spex.egg-info/dependency_links.txt
spex.egg-info/entry_points.txt
spex.egg-info/not-zip-safe
spex.egg-info/pbr.json
spex.egg-info/requires.txt
spex.egg-info/top_level.txt
spex/bin/__init__.py
spex/bin/args.py
spex/bin/spex.py
tests/conftest.py
tests/test_args.py
tests/test_artifact_server.py
tests/test_entrypoint.py
tests/test_runner.py
tests/test_spex.py
tests/bin/test_args.py
tests/data/.gitkeep