Metadata-Version: 1.0
Name: spex
Version: 0.2.0
Summary: PEX for PySpark
Home-page: https://github.com/URXTech/spex
Author: UNKNOWN
Author-email: bowyer@urx.com
License: Proprietary
Keywords: spex
Platform: UNKNOWN
